{"data":[{"name":"\uac15\uc57d\uad6d","addr":"\uc138\uc885\ud2b9\ubcc4\uc790\uce58\uc2dc \uae08\ub0a8\uba74 \uc6a9\ud3ec\ub85c 53"},{"name":"\ub298\ubd04\uc57d\uad6d","addr":"\uc138\uc885\ud2b9\ubcc4\uc790\uce58\uc2dc \ud55c\ub204\ub9ac\ub300\ub85c 2012"},{"name":"\ub300\uc138\uc628\ub204\ub9ac\uc57d\uad6d","addr":"\uc138\uc885\ud2b9\ubcc4\uc790\uce58\uc2dc \ud55c\ub204\ub9ac\ub300\ub85c 589"},{"name":"\ub354\uac74\uac15\ud55c\uc57d\uad6d","addr":"\uc138\uc885\ud2b9\ubcc4\uc790\uce58\uc2dc \ud55c\ub204\ub9ac\ub300\ub85c 1934"},{"name":"\ub370\uc77c\ub9ac\uc57d\uad6d","addr":"\uc138\uc885\ud2b9\ubcc4\uc790\uce58\uc2dc \ub3c4\uc6c01\ub85c 106"},{"name":"\ub4dc\ub9bc\uc57d\uad6d","addr":"\uc138\uc885\ud2b9\ubcc4\uc790\uce58\uc2dc \ud55c\ub204\ub9ac\ub300\ub85c 496"},{"name":"\uba54\ub514\ud31c365\uc57d\uad6d","addr":"\uc138\uc885\ud2b9\ubcc4\uc790\uce58\uc2dc \ud55c\ub204\ub9ac\ub300\ub85c 2264"},{"name":"\uba54\ub514\ud31c\ubcf4\ub77c\uc57d\uad6d","addr":"\uc138\uc885\ud2b9\ubcc4\uc790\uce58\uc2dc \ubcf4\ub4ec4\ub85c 9"},{"name":"\uba54\ub514\ud31c\uc138\uc885\uc57d\uad6d","addr":"\uc138\uc885\ud2b9\ubcc4\uc790\uce58\uc2dc \ud55c\ub204\ub9ac\ub300\ub85c 165"},{"name":"\uba54\ub514\ud31c\uc6b0\ub9ac\ub4e4\uc57d\uad6d","addr":"\uc138\uc885\ud2b9\ubcc4\uc790\uce58\uc2dc \ub2ec\ube5b\ub85c 59"},{"name":"\ubbf8\uc18c\uc57d\uad6d","addr":"\uc138\uc885\ud2b9\ubcc4\uc790\uce58\uc2dc \ud55c\ub204\ub9ac\ub300\ub85c 2016"},{"name":"\ubbfc\ud2b8\uc57d\uad6d","addr":"\uc138\uc885\ud2b9\ubcc4\uc790\uce58\uc2dc \uc138\uc885\ub85c 1219"},{"name":"\ubc14\ub2e4\uc57d\uad6d","addr":"\uc138\uc885\ud2b9\ubcc4\uc790\uce58\uc2dc \uc870\uce58\uc6d0\uc74d \uc870\uce58\uc6d0\ub85c 31"},{"name":"\ubcf4\ub78c\uc57d\uad6d","addr":"\uc138\uc885\ud2b9\ubcc4\uc790\uce58\uc2dc \ub0a8\uc138\uc885\ub85c 454"},{"name":"\uc0ac\ub791\uc628\ub204\ub9ac\uc57d\uad6d","addr":"\uc138\uc885\ud2b9\ubcc4\uc790\uce58\uc2dc \ud55c\ub204\ub9ac\ub300\ub85c 157"},{"name":"\uc0c8\ub86c\uac00\uc628\uc57d\uad6d","addr":"\uc138\uc885\ud2b9\ubcc4\uc790\uce58\uc2dc \uc0c8\ub86c\uc911\uc559\ub85c 62-15"},{"name":"\uc0c8\ub86c\uc815\uc57d\uad6d","addr":"\uc138\uc885\ud2b9\ubcc4\uc790\uce58\uc2dc \uc0c8\ub86c\uc911\uc559\ub85c 62-15"},{"name":"\uc0c8\ub86c\ud2bc\ud2bc\uc57d\uad6d","addr":"\uc138\uc885\ud2b9\ubcc4\uc790\uce58\uc2dc \uc0c8\ub86c\uc911\uc559\ub85c 47"},{"name":"\uc0c8\ube5b\uc57d\uad6d","addr":"\uc138\uc885\ud2b9\ubcc4\uc790\uce58\uc2dc \ubcf4\ub4ec3\ub85c 92"},{"name":"\uc0ec\ub86c\uc57d\uad6d","addr":"\uc138\uc885\ud2b9\ubcc4\uc790\uce58\uc2dc \uc870\uce58\uc6d0\uc74d \uc0c8\ub0b4\ub85c 72"},{"name":"\uc11c\uc6b8\uc57d\uad6d","addr":"\uc138\uc885\ud2b9\ubcc4\uc790\uce58\uc2dc \ub0a8\uc138\uc885\ub85c 450"},{"name":"\uc131\ubaa8\uc57d\uad6d","addr":"\uc138\uc885\ud2b9\ubcc4\uc790\uce58\uc2dc \uc870\uce58\uc6d0\uc74d \uc870\uce58\uc6d02\uae38 5 1\uce35"},{"name":"\uc138\uc778\uc57d\uad6d","addr":"\uc138\uc885\ud2b9\ubcc4\uc790\uce58\uc2dc \uc870\uce58\uc6d0\uc74d \uc0c8\ub0b4\ub85c 132"},{"name":"\uc138\uc885\ub9d1\uc740\uc57d\uad6d","addr":"\uc138\uc885\ud2b9\ubcc4\uc790\uce58\uc2dc \uc870\uce58\uc6d0\uc74d \ub3c4\uc6d01\ub85c 16"},{"name":"\uc138\uc885\uc911\uc559\uc57d\uad6d","addr":"\uc138\uc885\ud2b9\ubcc4\uc790\uce58\uc2dc \uc870\uce58\uc6d0\uc74d \ud5c8\ub9cc\uc11d\ub85c 69"},{"name":"\uc138\uc885\ud589\ubcf5\uc57d\uad6d","addr":"\uc138\uc885\ud2b9\ubcc4\uc790\uce58\uc2dc \ud55c\ub204\ub9ac\ub300\ub85c 583"},{"name":"\uc2e0\ud765\uc57d\uad6d","addr":"\uc138\uc885\ud2b9\ubcc4\uc790\uce58\uc2dc \uc870\uce58\uc6d0\uc74d \uc0c8\ub0b416\uae38 4"},{"name":"\uc544\ub984\uc218\uc57d\uad6d","addr":"\uc138\uc885\ud2b9\ubcc4\uc790\uce58\uc2dc \ubcf4\ub4ec3\ub85c 95"},{"name":"\uc544\uc774\ub9d8\uc57d\uad6d","addr":"\uc138\uc885\ud2b9\ubcc4\uc790\uce58\uc2dc \ubcf4\ub4ec3\ub85c 150"},{"name":"\uc5ed\uc804\uc57d\uad6d","addr":"\uc138\uc885\ud2b9\ubcc4\uc790\uce58\uc2dc \uc870\uce58\uc6d0\uc74d \uc73c\ub738\uae38 208"},{"name":"\uc5f4\ub9b0\uc57d\uad6d","addr":"\uc138\uc885\ud2b9\ubcc4\uc790\uce58\uc2dc \uc870\uce58\uc6d0\uc74d \uc0c8\ub0b4\ub85c 77-1"},{"name":"\uc6b0\ub9ac\ub4e4\uc57d\uad6d","addr":"\uc138\uc885\ud2b9\ubcc4\uc790\uce58\uc2dc \uc870\uce58\uc6d0\uc74d \uc870\uce58\uc6d0\ub85c 28"},{"name":"\uc7a5\uae30\uc57d\uad6d","addr":"\uc138\uc885\ud2b9\ubcc4\uc790\uce58\uc2dc \uc7a5\uad70\uba74 \uc7a5\ucc99\ub85c 402-1"},{"name":"\uc885\ub85c\uc57d\uad6d","addr":"\uc138\uc885\ud2b9\ubcc4\uc790\uce58\uc2dc \uc870\uce58\uc6d0\uc74d \uc870\uce58\uc6d0\ub85c 3"},{"name":"\ucc38\uace0\uc6b4\uc57d\uad6d","addr":"\uc138\uc885\ud2b9\ubcc4\uc790\uce58\uc2dc \ub9c8\uc74c\ub85c 70"},{"name":"\ucc9c\uc9c0\uc778\uc57d\uad6d","addr":"\uc138\uc885\ud2b9\ubcc4\uc790\uce58\uc2dc \ub204\ub9ac\ub85c 54"},{"name":"\uccad\uc554\uc57d\uad6d","addr":"\uc138\uc885\ud2b9\ubcc4\uc790\uce58\uc2dc \ud55c\ub204\ub9ac\ub300\ub85c 492"},{"name":"\ud558\ub098\uc57d\uad6d","addr":"\uc138\uc885\ud2b9\ubcc4\uc790\uce58\uc2dc \uc870\uce58\uc6d0\uc74d \uc0c8\ub0b4\ub85c 68"},{"name":"\ud55c\uc194\uc57d\uad6d","addr":"\uc138\uc885\ud2b9\ubcc4\uc790\uce58\uc2dc \ub204\ub9ac\ub85c 106"},{"name":"\ud574\ubc00\uc57d\uad6d","addr":"\uc138\uc885\ud2b9\ubcc4\uc790\uce58\uc2dc \ub9c8\uc74c\ub85c 78"},{"name":"\ud5c8\uc57d\uad6d","addr":"\uc138\uc885\ud2b9\ubcc4\uc790\uce58\uc2dc \uc870\uce58\uc6d0\uc74d \uc870\uce58\uc6d0\ub85c 42-2"}]}