{"data":[{"name":"\uac74\uac15\ub9c8\ud2b8\uc57d\uad6d","addr":"\uc804\ub77c\ub0a8\ub3c4 \uc644\ub3c4\uad70 \uc644\ub3c4\uc74d \uc7a5\ubcf4\uace0\ub300\ub85c 264","tel":"0615522460"},{"name":"\uae08\uc77c\uac74\uac15\uc57d\uad6d","addr":"\uc804\ub77c\ub0a8\ub3c4 \uc644\ub3c4\uad70 \uae08\uc77c\uc74d \uae08\uc77c\ub85c 390","tel":"0615521940"},{"name":"\ub0a8\uc77c\uc57d\uad6d","addr":"\uc804\ub77c\ub0a8\ub3c4 \uc644\ub3c4\uad70 \uc644\ub3c4\uc74d \uac1c\ud3ec\ub85c130\ubc88\uae38 17","tel":"0615542279"},{"name":"\ub3c4\ubbf8\uc57d\uad6d","addr":"\uc804\ub77c\ub0a8\ub3c4 \uc644\ub3c4\uad70 \uc644\ub3c4\uc74d \uc7a5\ubcf4\uace0\ub300\ub85c 282","tel":"0615541615"},{"name":"\ubc31\uc81c\uc57d\uad6d","addr":"\uc804\ub77c\ub0a8\ub3c4 \uc644\ub3c4\uad70 \uc644\ub3c4\uc74d \uac1c\ud3ec\ub85c 154-7","tel":"0615552460"},{"name":"\uc0c8\uae08\uc77c\uc57d\uad6d","addr":"\uc804\ub77c\ub0a8\ub3c4 \uc644\ub3c4\uad70 \uae08\uc77c\uc74d \uae08\uc77c\ub85c 391","tel":"0615532107"},{"name":"\uc18c\uc548\ud558\ub298\uc57d\uad6d","addr":"\uc804\ub77c\ub0a8\ub3c4 \uc644\ub3c4\uad70 \uc18c\uc548\uba74 \uc18c\uc548\ub85c 187-2","tel":"0615540017"},{"name":"\uccad\uc0b0\uc57d\uad6d","addr":"\uc804\ub77c\ub0a8\ub3c4 \uc644\ub3c4\uad70 \uccad\uc0b0\uba74 \uccad\uc0b0\ub85c 1619-3","tel":"0615521996"},{"name":"\ud558\ub098\ub85c\uc57d\uad6d","addr":"\uc804\ub77c\ub0a8\ub3c4 \uc644\ub3c4\uad70 \uc644\ub3c4\uc74d \uccad\ud574\uc9c4\ub3d9\ub85c 66","tel":"0615542526"}]}