{"data":[{"name":"\uad11\uba85\uc57d\uad6d","addr":"\ucda9\uccad\ub0a8\ub3c4 \uc11c\uc0b0\uc2dc \uace0\ubd81\uba74 \uace0\ubd811\ub85c 291"},{"name":"\uad8c\uc57d\uad6d","addr":"\ucda9\uccad\ub0a8\ub3c4 \uc11c\uc0b0\uc2dc \uc2dc\uc7a56\ub85c 30-15"},{"name":"\ub2e4\uc0ac\ub791\uc57d\uad6d","addr":"\ucda9\uccad\ub0a8\ub3c4 \uc11c\uc0b0\uc2dc \ub0a8\ubd80\uc21c\ud658\ub85c 1025"},{"name":"\ub300\uc0b0\ud504\ub77c\uc790\uc57d\uad6d","addr":"\ucda9\uccad\ub0a8\ub3c4 \uc11c\uc0b0\uc2dc \ub300\uc0b0\uc74d \uad6c\uc9c4\ucc9c\ub85c 12"},{"name":"\ub354\ube14\uc720\uc2a4\ud1a0\uc5b4\ub300\ud765\uc57d\uad6d","addr":"\ucda9\uccad\ub0a8\ub3c4 \uc11c\uc0b0\uc2dc \uc548\uacac\ub85c 184-2"},{"name":"\ub3c4\ubbf8\ub2f9\uc57d\uad6d","addr":"\ucda9\uccad\ub0a8\ub3c4 \uc11c\uc0b0\uc2dc \uc548\uacac\ub85c 185"},{"name":"\ub3c5\uc77c\uc57d\uad6d","addr":"\ucda9\uccad\ub0a8\ub3c4 \uc11c\uc0b0\uc2dc \uc2dc\uc7a56\ub85c 37"},{"name":"\ub8e8\ube44\uc57d\uad6d","addr":"\ucda9\uccad\ub0a8\ub3c4 \uc11c\uc0b0\uc2dc \uc548\uacac\ub85c 175"},{"name":"\ubb34\uad81\ud654\uc57d\uad6d","addr":"\ucda9\uccad\ub0a8\ub3c4 \uc11c\uc0b0\uc2dc \uc6b4\uc0b0\uba74 \uc6b4\uc554\ub85c 1053"},{"name":"\ubbf8\uc18c\uc57d\uad6d","addr":"\ucda9\uccad\ub0a8\ub3c4 \uc11c\uc0b0\uc2dc \uc548\uacac\ub85c 180"},{"name":"\ubc15\uc6a9\ub450\uc57d\uad6d","addr":"\ucda9\uccad\ub0a8\ub3c4 \uc11c\uc0b0\uc2dc \uc548\uacac\ub85c 184-6"},{"name":"\ubcf4\ub8e1\uc57d\uad6d","addr":"\ucda9\uccad\ub0a8\ub3c4 \uc11c\uc0b0\uc2dc \uc131\uc5f0\uba74 \uc131\uc5f03\ub85c 45"},{"name":"\ubd80\ucd98\uc57d\uad6d","addr":"\ucda9\uccad\ub0a8\ub3c4 \uc11c\uc0b0\uc2dc \ub300\uc0ac\ub3d94\uae38 7-4"},{"name":"\uc0bc\ud654\uc57d\uad6d","addr":"\ucda9\uccad\ub0a8\ub3c4 \uc11c\uc0b0\uc2dc \ubc88\ud6542\ub85c 32"},{"name":"\uc0c1\uad6c\uc57d\uad6d","addr":"\ucda9\uccad\ub0a8\ub3c4 \uc11c\uc0b0\uc2dc \ud574\ubbf8\uba74 \ub0a8\ubb385\ub85c 18"},{"name":"\uc11c\ub839\ub2f9\uc57d\uad6d","addr":"\ucda9\uccad\ub0a8\ub3c4 \uc11c\uc0b0\uc2dc \ubc88\ud6542\ub85c 15-2"},{"name":"\uc11c\ubb38\uc57d\uad6d","addr":"\ucda9\uccad\ub0a8\ub3c4 \uc11c\uc0b0\uc2dc \uc548\uacac\ub85c 191"},{"name":"\uc11c\uc0b0\uc57d\uad6d","addr":"\ucda9\uccad\ub0a8\ub3c4 \uc11c\uc0b0\uc2dc \uc11d\ub9bc4\ub85c 87"},{"name":"\uc11c\uc6b8\uc57d\uad6d","addr":"\ucda9\uccad\ub0a8\ub3c4 \uc11c\uc0b0\uc2dc \uc2dc\uc7a56\ub85c 27"},{"name":"\uc131\ubaa8\uc57d\uad6d","addr":"\ucda9\uccad\ub0a8\ub3c4 \uc11c\uc0b0\uc2dc \uace0\uc6b4\ub85c 219"},{"name":"\uc138\uc120\uc57d\uad6d","addr":"\ucda9\uccad\ub0a8\ub3c4 \uc11c\uc0b0\uc2dc \ud574\ubbf8\uba74 \ub0a8\ubb384\ub85c 17-1"},{"name":"\uc194\ub0b4\uc74c\uc57d\uad6d","addr":"\ucda9\uccad\ub0a8\ub3c4 \uc11c\uc0b0\uc2dc \uc131\uc5f0\uba74 \uc131\uc5f03\ub85c 53"},{"name":"\uc218\uc57d\uad6d","addr":"\ucda9\uccad\ub0a8\ub3c4 \uc11c\uc0b0\uc2dc \uc2dc\uc7a56\ub85c 30"},{"name":"\uc601\uc131\uc57d\uad6d","addr":"\ucda9\uccad\ub0a8\ub3c4 \uc11c\uc0b0\uc2dc \uc2dc\uc7a54\uae38 10"},{"name":"\uc624\uc131\uc57d\uad6d","addr":"\ucda9\uccad\ub0a8\ub3c4 \uc11c\uc0b0\uc2dc \ub300\uc0ac\ub3d91\ub85c 16"},{"name":"\uc6b0\ub9ac\uc57d\uad6d","addr":"\ucda9\uccad\ub0a8\ub3c4 \uc11c\uc0b0\uc2dc \ud638\uc218\uacf5\uc6d015\ub85c 7-6"},{"name":"\uc720\ud654\uc57d\uad6d","addr":"\ucda9\uccad\ub0a8\ub3c4 \uc11c\uc0b0\uc2dc \ubc88\ud6541\ub85c 12-1"},{"name":"\uc815\ub2e4\uc6b4\uc57d\uad6d","addr":"\ucda9\uccad\ub0a8\ub3c4 \uc11c\uc0b0\uc2dc \ubd80\ucd981\ub85c 34-1"},{"name":"\uc815\uc57d\uad6d","addr":"\ucda9\uccad\ub0a8\ub3c4 \uc11c\uc0b0\uc2dc \uc548\uacac\ub85c 284"},{"name":"\uc81c\uc77c\uc57d\uad6d","addr":"\ucda9\uccad\ub0a8\ub3c4 \uc11c\uc0b0\uc2dc \uc2dc\uc7a53\uae38 26"},{"name":"\uc9c0\uace1\ubc31\ud654\uc810\uc57d\uad6d","addr":"\ucda9\uccad\ub0a8\ub3c4 \uc11c\uc0b0\uc2dc \uc9c0\uace1\uba74 \ucda9\uc758\ub85c 1192"},{"name":"\ud130\ubbf8\ub110\uc57d\uad6d","addr":"\ucda9\uccad\ub0a8\ub3c4 \uc11c\uc0b0\uc2dc \uc548\uacac\ub85c 190"},{"name":"\ud478\ub978\uc57d\uad6d","addr":"\ucda9\uccad\ub0a8\ub3c4 \uc11c\uc0b0\uc2dc \uc11d\ub9bc4\ub85c 90"},{"name":"\ud574\ubbf8\uc57d\uad6d","addr":"\ucda9\uccad\ub0a8\ub3c4 \uc11c\uc0b0\uc2dc \ud574\ubbf8\uba74 \ub0a8\ubb385\ub85c 13"}]}