{"data":[{"name":"\uac10\ucd08\ub2f9\uc57d\uad6d","addr":"\ucda9\uccad\ubd81\ub3c4 \uc81c\ucc9c\uc2dc \uccad\ud48d\ud638\ub85c 100","tel":"0436456102"},{"name":"\ub098\uc740\uc57d\uad6d","addr":"\ucda9\uccad\ubd81\ub3c4 \uc81c\ucc9c\uc2dc \uc6a9\ub450\ucc9c\ub85c 51","tel":"0439201114"},{"name":"\ub0a8\ucc9c\uc57d\uad6d","addr":"\ucda9\uccad\ubd81\ub3c4 \uc81c\ucc9c\uc2dc \ud48d\uc591\ub85c 120","tel":"0436472286"},{"name":"\ub3d9\uc0b0\uc57d\uad6d","addr":"\ucda9\uccad\ubd81\ub3c4 \uc81c\ucc9c\uc2dc \uc758\ubcd1\ub300\ub85c 88","tel":"0436473013"},{"name":"\ub450\uc190\uc628\ub204\ub9ac\uc57d\uad6d","addr":"\ucda9\uccad\ubd81\ub3c4 \uc81c\ucc9c\uc2dc \uc758\ub9bc\ub300\ub85c 222","tel":"0436451722"},{"name":"\ub4dc\ub9bc\uc57d\uad6d","addr":"\ucda9\uccad\ubd81\ub3c4 \uc81c\ucc9c\uc2dc \uc6a9\ub450\ucc9c\ub85c 117","tel":"0436538993"},{"name":"\uc0c8\uc0ac\ub791\uc57d\uad6d","addr":"\ucda9\uccad\ubd81\ub3c4 \uc81c\ucc9c\uc2dc \uc758\ub9bc\ub300\ub85c 15","tel":"0436440211"},{"name":"\uc131\ubbfc\uc57d\uad6d","addr":"\ucda9\uccad\ubd81\ub3c4 \uc81c\ucc9c\uc2dc \ub355\uc0b0\uba74 \uc57d\ucd08\ub85c3\uae38 3-1","tel":"0436423207"},{"name":"\uc18c\ub098\ubb34\uc57d\uad6d","addr":"\ucda9\uccad\ubd81\ub3c4 \uc81c\ucc9c\uc2dc \ud558\uc18c\ub85c 64","tel":"0436535432"},{"name":"\uc218\uc0b0\uc57d\uad6d","addr":"\ucda9\uccad\ubd81\ub3c4 \uc81c\ucc9c\uc2dc \uc218\uc0b0\uba74 \uc6d4\uc545\ub85c26\uae38 52-1","tel":"0436485129"},{"name":"\uc628\ub204\ub9ac\uac74\uac15\uc57d\uad6d","addr":"\ucda9\uccad\ubd81\ub3c4 \uc81c\ucc9c\uc2dc \uc758\ubcd1\ub300\ub85c 233","tel":"0436424300"},{"name":"\uc6b0\ub9ac\uba54\ub514\uceec\uc57d\uad6d","addr":"\ucda9\uccad\ubd81\ub3c4 \uc81c\ucc9c\uc2dc \uc758\ub9bc\ub300\ub85c 128","tel":"0436433381"},{"name":"\uc774\ud654\uc57d\uad6d","addr":"\ucda9\uccad\ubd81\ub3c4 \uc81c\ucc9c\uc2dc \uc758\ubcd1\ub300\ub85c 111","tel":"0436430609"},{"name":"\uc815\uc57d\uad6d","addr":"\ucda9\uccad\ubd81\ub3c4 \uc81c\ucc9c\uc2dc \uc7a5\ud3c9\ucc9c\ub85c 11","tel":"0436451557"},{"name":"\uc911\uc559\ub85c\uc57d\uad6d","addr":"\ucda9\uccad\ubd81\ub3c4 \uc81c\ucc9c\uc2dc \uc758\ub9bc\ub300\ub85c14\uae38 4","tel":"0436473511"},{"name":"\ucc29\ud55c\uc57d\uad6d","addr":"\ucda9\uccad\ubd81\ub3c4 \uc81c\ucc9c\uc2dc \uc758\ub9bc\ub300\ub85c 90-1","tel":"0436421245"},{"name":"\ud558\uc18c\uc57d\uad6d","addr":"\ucda9\uccad\ubd81\ub3c4 \uc81c\ucc9c\uc2dc \ud558\uc18c\ub85c 74","tel":"436425198"},{"name":"\ud589\ubcf5\ud55c\uc57d\uad6d","addr":"\ucda9\uccad\ubd81\ub3c4 \uc81c\ucc9c\uc2dc \uc758\ubcd1\ub300\ub85c 107","tel":"0436470049"}]}